MANIFEST.in
README.rst
setup.py
docs/HISTORY.txt
docs/LICENSE.GPL
docs/LICENSE.txt
ftw/__init__.py
ftw.dashboard.portlets.postit.egg-info/PKG-INFO
ftw.dashboard.portlets.postit.egg-info/SOURCES.txt
ftw.dashboard.portlets.postit.egg-info/dependency_links.txt
ftw.dashboard.portlets.postit.egg-info/entry_points.txt
ftw.dashboard.portlets.postit.egg-info/namespace_packages.txt
ftw.dashboard.portlets.postit.egg-info/not-zip-safe
ftw.dashboard.portlets.postit.egg-info/requires.txt
ftw.dashboard.portlets.postit.egg-info/top_level.txt
ftw/dashboard/__init__.py
ftw/dashboard/portlets/__init__.py
ftw/dashboard/portlets/postit/__init__.py
ftw/dashboard/portlets/postit/configure.zcml
ftw/dashboard/portlets/postit/browser/__init__.py
ftw/dashboard/portlets/postit/browser/configure.zcml
ftw/dashboard/portlets/postit/browser/ftw_formhelper.py
ftw/dashboard/portlets/postit/browser/postit.py
ftw/dashboard/portlets/postit/browser/resources/bg_postit.jpg
ftw/dashboard/portlets/postit/browser/resources/ftwportlets.css
ftw/dashboard/portlets/postit/browser/resources/icon_remove_box.gif
ftw/dashboard/portlets/postit/browser/resources/postit.js
ftw/dashboard/portlets/postit/browser/templates/postit.pt
ftw/dashboard/portlets/postit/locales/ftw.dashboard.portlets.postit-manual.pot
ftw/dashboard/portlets/postit/locales/ftw.dashboard.portlets.postit.pot
ftw/dashboard/portlets/postit/locales/plone.pot
ftw/dashboard/portlets/postit/locales/de/LC_MESSAGES/ftw.dashboard.portlets.postit.po
ftw/dashboard/portlets/postit/locales/de/LC_MESSAGES/plone.po
ftw/dashboard/portlets/postit/locales/fr/LC_MESSAGES/ftw.dashboard.portlets.postit.po
ftw/dashboard/portlets/postit/locales/fr/LC_MESSAGES/plone.po
ftw/dashboard/portlets/postit/profiles/default/cssregistry.xml
ftw/dashboard/portlets/postit/profiles/default/jsregistry.xml
ftw/dashboard/portlets/postit/profiles/default/metadata.xml
ftw/dashboard/portlets/postit/profiles/default/portlets.xml
ftw/dashboard/portlets/postit/profiles/default/propertiestool.xml