Metadata-Version: 1.0
Name: ftw.dashboard.portlets.postit
Version: 1.3.2
Summary: Postit portlet for the dashboard
Home-page: https://github.com/4teamwork/ftw.dashboard.portlets.postit
Author: philippe gross
Author-email: mailto:info@4teamwork.ch
License: GPL2
Platform: UNKNOWN
Classifier: Programming Language :: Python
Classifier: Framework :: Plone
Classifier: Framework :: Plone :: 4.0
Classifier: Topic :: Software Development :: Libraries :: Python Modules
